inmemorystorage/__init__.py
inmemorystorage/storage.py
inmemorystorage/test_settings.py
dj_inmemorystorage-2.1.0.dist-info/LICENSE
dj_inmemorystorage-2.1.0.dist-info/METADATA
dj_inmemorystorage-2.1.0.dist-info/WHEEL
dj_inmemorystorage-2.1.0.dist-info/top_level.txt
dj_inmemorystorage-2.1.0.dist-info/zip-safe
dj_inmemorystorage-2.1.0.dist-info/RECORD
